Metadata-Version: 2.1
Name: DE-GeraAquivos
Version: 0.0.2
Summary: Gera arquivos baseado em dataframe
Home-page: https://github.com/almirjgomes/DE_GeraAquivos.git
Author: Almir J Gomes
Author-email: almir.jg@hotmail.com
License: MIT
Platform: UNKNOWN
